[{"C01":"1","C02":"Slovensk\u00e1 \u013eudov\u00e1 strana Andreja Hlinku","C03":"2","C04":"0,21","C05":"0","C06":"0,00"},{"C01":"2","C02":"DOBR\u00c1 VO\u013dBA","C03":"24","C04":"2,52","C05":"17","C06":"70,83"},{"C01":"3","C02":"Sloboda a Solidarita","C03":"71","C04":"7,45","C05":"57","C06":"80,28"},{"C01":"4","C02":"SME RODINA","C03":"128","C04":"13,44","C05":"98","C06":"76,56"},{"C01":"6","C02":"ZA \u013dUD\u00cd","C03":"35","C04":"3,67","C05":"30","C06":"85,71"},{"C01":"7","C02":"M\u00c1ME TOHO DOS\u0164 !","C03":"4","C04":"0,42","C05":"1","C06":"25,00"},{"C01":"9","C02":"Slovensk\u00e1 n\u00e1rodn\u00e1 strana","C03":"22","C04":"2,31","C05":"16","C06":"72,72"},{"C01":"11","C02":"OBY\u010cAJN\u00cd \u013dUDIA a nez\u00e1visl\u00e9 osobnosti (O\u013dANO), NOVA, Kres\u0165ansk\u00e1 \u00fania (K\u00da), ZMENA ZDOLA","C03":"242","C04":"25,42","C05":"186","C06":"76,85"},{"C01":"12","C02":"Koal\u00edcia Progres\u00edvne Slovensko a SPOLU - ob\u010dianska demokracia","C03":"42","C04":"4,41","C05":"30","C06":"71,42"},{"C01":"15","C02":"Kres\u0165anskodemokratick\u00e9 hnutie","C03":"34","C04":"3,57","C05":"27","C06":"79,41"},{"C01":"17","C02":"VLAS\u0164","C03":"28","C04":"2,94","C05":"19","C06":"67,85"},{"C01":"18","C02":"MOST - H\u00cdD","C03":"5","C04":"0,52","C05":"3","C06":"60,00"},{"C01":"19","C02":"SMER - soci\u00e1lna demokracia","C03":"202","C04":"21,21","C05":"164","C06":"81,18"},{"C01":"24","C02":"Kotlebovci - \u013dudov\u00e1 strana Na\u0161e Slovensko","C03":"110","C04":"11,55","C05":"77","C06":"70,00"},{"C01":"25","C02":"Socialisti.sk","C03":"3","C04":"0,31","C05":"2","C06":"66,66"}]