[{"C01":"1","C02":"Slovensk\u00e1 \u013eudov\u00e1 strana Andreja Hlinku","C03":"1","C04":"0,14","C05":"1","C06":"100,00"},{"C01":"2","C02":"DOBR\u00c1 VO\u013dBA","C03":"36","C04":"5,17","C05":"36","C06":"100,00"},{"C01":"3","C02":"Sloboda a Solidarita","C03":"14","C04":"2,01","C05":"14","C06":"100,00"},{"C01":"4","C02":"SME RODINA","C03":"58","C04":"8,33","C05":"58","C06":"100,00"},{"C01":"6","C02":"ZA \u013dUD\u00cd","C03":"34","C04":"4,88","C05":"33","C06":"97,05"},{"C01":"7","C02":"M\u00c1ME TOHO DOS\u0164 !","C03":"2","C04":"0,28","C05":"2","C06":"100,00"},{"C01":"9","C02":"Slovensk\u00e1 n\u00e1rodn\u00e1 strana","C03":"32","C04":"4,59","C05":"31","C06":"96,87"},{"C01":"10","C02":"Demokratick\u00e1 strana","C03":"8","C04":"1,14","C05":"8","C06":"100,00"},{"C01":"11","C02":"OBY\u010cAJN\u00cd \u013dUDIA a nez\u00e1visl\u00e9 osobnosti (O\u013dANO), NOVA, Kres\u0165ansk\u00e1 \u00fania (K\u00da), ZMENA ZDOLA","C03":"235","C04":"33,76","C05":"233","C06":"99,14"},{"C01":"12","C02":"Koal\u00edcia Progres\u00edvne Slovensko a SPOLU - ob\u010dianska demokracia","C03":"19","C04":"2,72","C05":"19","C06":"100,00"},{"C01":"13","C02":"STAROSTOVIA A NEZ\u00c1VISL\u00cd KANDID\u00c1TI","C03":"1","C04":"0,14","C05":"1","C06":"100,00"},{"C01":"14","C02":"99 % - ob\u010diansky hlas","C03":"1","C04":"0,14","C05":"1","C06":"100,00"},{"C01":"15","C02":"Kres\u0165anskodemokratick\u00e9 hnutie","C03":"110","C04":"15,80","C05":"110","C06":"100,00"},{"C01":"17","C02":"VLAS\u0164","C03":"19","C04":"2,72","C05":"19","C06":"100,00"},{"C01":"18","C02":"MOST - H\u00cdD","C03":"2","C04":"0,28","C05":"2","C06":"100,00"},{"C01":"19","C02":"SMER - soci\u00e1lna demokracia","C03":"101","C04":"14,51","C05":"99","C06":"98,01"},{"C01":"24","C02":"Kotlebovci - \u013dudov\u00e1 strana Na\u0161e Slovensko","C03":"18","C04":"2,58","C05":"18","C06":"100,00"},{"C01":"25","C02":"Socialisti.sk","C03":"5","C04":"0,71","C05":"5","C06":"100,00"}]